google_recaptcha/__init__.py
google_recaptcha/recaptcha.py
google_recaptcha/templates/recaptcha_v2.html
google_recaptcha/templates/recaptcha_v3.html
google_recaptcha-2.0.0.dist-info/LICENSE
google_recaptcha-2.0.0.dist-info/WHEEL
google_recaptcha-2.0.0.dist-info/METADATA
google_recaptcha-2.0.0.dist-info/RECORD
