Metadata-Version: 2.1
Name: google-recaptcha
Version: 2.0.0
Summary: Google recaptcha helps you protect your web form by using google's latest recaptcha (Completely Automated Public Turing test to tell Computers and Humans Apart) technology.
Home-page: https://github.com/jpraychev/google-recaptcha
License: MIT
Keywords: recaptcha,google recaptcha
Author: Jordan Raychev
Author-email: jpraychev@gmail.com
Maintainer: Jordan Raychev
Maintainer-email: jpraychev@gmail.com
Requires-Python: >=3.7,<4.0
Classifier: License :: OSI Approved :: MIT License
Classifier: Programming Language :: Python :: 3
Classifier: Programming Language :: Python :: 3.7
Classifier: Programming Language :: Python :: 3.8
Classifier: Programming Language :: Python :: 3.9
Classifier: Programming Language :: Python :: 3.10
Classifier: Topic :: Software Development :: Libraries :: Python Modules
Requires-Dist: Flask (>=2.2.2,<3.0.0)
Requires-Dist: requests (>=2.28.1,<3.0.0)
Project-URL: Repository, https://github.com/jpraychev/google-recaptcha
